Workbook

Sheet STOCKSHEET
B1: REST PERK STOCKSHEET
B2: 46023
A3: DATE | B3: ITEMS IN STORE | C3: OPENING STOCK | D3: PURCHASES IN | E3: STOCK OUT | F3: CLOSING BALANCE | G3: UNIT COST | H3: OPENING STOCK | I3: PURCHASES IN | J3: UNIT PRICE | K3: STOCK OUT
A4: 46023 | B4: TISSUES | C4: =TISSUES!B53 -> 218 | D4: =TISSUES!C53 -> 0 | E4: =TISSUES!D53 -> 138 | F4: =C4+D4-E4 -> 80 | G4: 20 | H4: =C4*G4 -> 4360 | I4: =G4*D4 -> 0 | J4: 0 | K4: =E4*J4 -> 0
A5: 46023 | B5: SAWA SOAP | C5: ='SAWA SOAP'!B28 -> 269 | D5: ='SAWA SOAP'!C28 -> 432 | E5: ='SAWA SOAP'!D28 -> 269 | F5: =C5+D5-E5 -> 432 | G5: =885/144 -> 6.1458333 | H5: =G5*C5 -> 1653.2292 | I5: =G5*D5 -> 2655 | J5: 0 | K5: =E5*J5 -> 0
A6: 46023 | B6: WATER 1LT | C6: ='WATER 1LT'!B35 -> 42 | D6: ='WATER 1LT'!C35 -> 0 | E6: ='WATER 1LT'!D35 -> 30 | F6: =C6+D6-E6 -> 12 | G6: =400/12 -> 33.333333 | H6: =G6*C6 -> 1400 | I6: =G6*D6 -> 0 | J6: 100 | K6: =J6*E6 -> 3000
A7: 46023 | B7: WATER 500ML FOR SALES | C7: ='WATER 500ML'!B38 -> 88 | D7: ='WATER 500ML'!C38 -> 48 | E7: ='WATER 500ML'!D38-STOCKSHEET!E8 -> 64 | F7: =C7+D7-E7-E8 -> 72 | G7: =400/24 -> 16.666667 | H7: =G7*C7 -> 1466.6667 | I7: =G7*D7 -> 800 | J7: 50 | K7: =E7*J7 -> 3200
A8: 46023 | B8: WATER 500ML FOR THE ROOMS | C8: 0 | D8: 0 | E8: ='[1]R.ANALYSIS JANUARY'!$E$33 -> 0 | F8: 0 | G8: 16.666667 | H8: =G8*C8 -> 0 | I8: =G8*D8 -> 0 | J8: 0 | K8: =E8*J8 -> 0
A9: 46023 | B9: TRUST | C9: =TRUST!B28 -> 52 | D9: =TRUST!C28 -> 48 | E9: =TRUST!D28 -> 28 | F9: =C9+D9-E9 -> 72 | G9: =590/24 -> 24.583333 | H9: =G9*C9 -> 1278.3333 | I9: =G9*D9 -> 1180 | J9: 100 | K9: =E9*J9 -> 2800
A10: 46023 | B10: VASELINE | C10: =VASELINE!B28 -> 16 | D10: =VASELINE!C28 -> 24 | E10: =VASELINE!D28 -> 16 | F10: =C10+D10-E10 -> 24 | G10: =460/12 -> 38.333333 | H10: =G10*C10 -> 613.33333 | I10: =G10*D10 -> 920 | J10: 50 | K10: =E10*J10 -> 800
A11: 46023 | B11: TOOTHPASTE & BRUSH | C11: ='TOOTHPASTE & BRUSH'!B28 -> 137 | D11: ='TOOTHPASTE & BRUSH'!C28 -> 0 | E11: ='TOOTHPASTE & BRUSH'!D28 -> 23 | F11: =C11+D11-E11 -> 114 | G11: 20 | H11: =G11*C11 -> 2740 | I11: =G11*D11 -> 0 | J11: 50 | K11: =E11*J11 -> 1150
A12: 46023 | B12: SODA 500ML | C12: ='SODA 500ML'!B28 -> 43 | D12: ='SODA 500ML'!C28 -> 0 | E12: ='SODA 500ML'!D28 -> 19 | F12: =C12+D12-E12 -> 24 | G12: =1475/24 -> 61.458333 | H12: =G12*C12 -> 2642.7083 | I12: =G12*D12 -> 0 | J12: 100 | K12: =E12*J12 -> 1900
A13: 46023 | B13: PREDATOR 500ML | C13: ='PREDATOR 500ML'!B28 -> 11 | D13: ='PREDATOR 500ML'!C28 -> 0 | E13: ='PREDATOR 500ML'!D28 -> 11 | F13: =C13+D13-E13 -> 0 | G13: =650/12 -> 54.166667 | H13: =G13*C13 -> 595.83333 | I13: =G13*D13 -> 0 | J13: 100 | K13: =E13*J13 -> 1100
A14: 46023 | B14: PANADOL EXTRA | C14: ='PANADOL EXTRA'!B28 -> 120 | D14: ='PANADOL EXTRA'!C28 -> 0 | E14: ='PANADOL EXTRA'!D28 -> 20 | F14: =C14+D14-E14 -> 100 | G14: =550/100 -> 5.5 | H14: =G14*C14 -> 660 | I14: =G14*D14 -> 0 | J14: 30 | K14: =(E14/2)*J14 -> 300
A15: 46023 | B15: MARA MOJA | C15: ='MARA MOJA '!B28 -> 118 | D15: ='MARA MOJA '!C28 -> 0 | E15: ='MARA MOJA '!D28 -> 18 | F15: =C15+D15-E15 -> 100 | G15: =355/100 -> 3.55 | H15: =G15*C15 -> 418.9 | I15: =G15*D15 -> 0 | J15: 20 | K15: =(E15/2)*J15 -> 180
A16: 46023 | B16: VIM | C16: ='VIM 500GM'!B4 -> 13 | D16: ='VIM 500GM'!C28 -> 0 | E16: ='VIM 500GM'!D28 -> 1 | F16: =C16+D16-E16 -> 12 | G16: =2270/24 -> 94.583333 | H16: =G16*C16 -> 1229.5833 | I16: =G16*D16 -> 0 | J16: 0 | K16: =E16*J16 -> 0
B17: TOTALS | C17: =SUM(C4:C16) -> 1127 | D17: =SUM(D4:D16) -> 552 | E17: =SUM(E4:E16) -> 637 | F17: =SUM(F4:F16) -> 1042 | H17: =SUM(H4:H16) -> 19058.588 | I17: =SUM(I4:I16) -> 5555 | K17: =SUM(K4:K16) -> 14430

Sheet TISSUES
B2: OPENING STOCK
A3: DATE | B3: TOTAL STOCK 1 JAN | C3: PURCHASED | D3: STOCK OUT | E3: BALANCE IN STORE
A4: 46023 | B4: =40+18+160 -> 218 | D4: =40+18 -> 58 | E4: =B4+C4-D4 -> 160
A5: 46296 | D5: 40 | E5: =E4+B5+C5-D5 -> 120
A6: 14/1 2026 | D6: 40 | E6: =E5+B6+C6-D6 -> 80
E7: =E6+B7+C7-D7 -> 80
E8: =E7+B8+C8-D8 -> 80
E9: =E8+B9+C9-D9 -> 80
E10: =E9+B10+C10-D10 -> 80
E11: =E10+B11+C11-D11 -> 80
E12: =E11+B12+C12-D12 -> 80
E13: =E12+B13+C13-D13 -> 80
E14: =E13+B14+C14-D14 -> 80
E15: =E14+B15+C15-D15 -> 80
E16: =E15+B16+C16-D16 -> 80
E17: =E16+B17+C17-D17 -> 80
E18: =E17+B18+C18-D18 -> 80
... E52: =E51+B52+C52-D52 -> 80
A53: TOTALS | B53: =SUM(B4:B52) -> 218 | C53: =SUM(C4:C52) -> 0 | D53: =SUM(D4:D52) -> 138

Sheet SAWA SOAP
B2: OPENING STOCK
A3: DATE | B3: SAWA SOAP | C3: PURCHASE | D3: STOCK OUT | E3: BALANCE
A4: 46023 | B4: =45+62+18+144 -> 269 | D4: =45+62+18 -> 125 | E4: =B4+C4-D4 -> 144
A5: 14/1/2026 | D5: 144 | E5: =E4+B5+C5-D5 -> 0
A6: 16/1/2026 | C6: =144*3 -> 432 | E6: =E5+B6+C6-D6 -> 432
E7: =E6+B7+C7-D7 -> 432
E8: =E7+B8+C8-D8 -> 432
E9: =E8+B9+C9-D9 -> 432
E10: =E9+B10+C10-D10 -> 432
E11: =E10+B11+C11-D11 -> 432
E12: =E11+B12+C12-D12 -> 432
E13: =E12+B13+C13-D13 -> 432
E14: =E13+B14+C14-D14 -> 432
E15: =E14+B15+C15-D15 -> 432
E16: =E15+B16+C16-D16 -> 432
E17: =E16+B17+C17-D17 -> 432
E18: =E17+B18+C18-D18 -> 432
... E27: =E26+B27+C27-D27 -> 432
A28: TOTALS | B28: =SUM(B4:B27) -> 269 | C28: =SUM(C4:C27) -> 432 | D28: =SUM(D4:D27) -> 269

Sheet WATER 1LT
B2: OPENING STOCK
A3: DATE | B3: WATER 1LT | C3: PURCHASE | D3: STOCK OUT | E3: BALANCE IN STORE
A4: 46023 | B4: =12+6+24 -> 42 | D4: =12+6 -> 18 | E4: =B4+C4-D4 -> 24
A5: 14/1/2026 | D5: 12 | E5: =E4+B5+C5-D5 -> 12
E6: =E5+B6+C6-D6 -> 12
E7: =E6+B7+C7-D7 -> 12
E8: =E7+B8+C8-D8 -> 12
E9: =E8+B9+C9-D9 -> 12
E10: =E9+B10+C10-D10 -> 12
E11: =E10+B11+C11-D11 -> 12
E12: =E11+B12+C12-D12 -> 12
E13: =E12+B13+C13-D13 -> 12
E14: =E13+B14+C14-D14 -> 12
E15: =E14+B15+C15-D15 -> 12
E16: =E15+B16+C16-D16 -> 12
E17: =E16+B17+C17-D17 -> 12
E18: =E17+B18+C18-D18 -> 12 | G18: =+G14 -> 0
E19: =E18+B19+C19-D19 -> 12
E20: =E19+B20+C20-D20 -> 12
E21: =E20+B21+C21-D21 -> 12
E22: =E21+B22+C22-D22 -> 12
E23: =E22+B23+C23-D23 -> 12
E24: =E23+B24+C24-D24 -> 12
E25: =E24+B25+C25-D25 -> 12
E26: =E25+B26+C26-D26 -> 12
E27: =E26+B27+C27-D27 -> 12
E28: =E27+B28+C28-D28 -> 12
E29: =E28+B29+C29-D29 -> 12
E30: =E29+B30+C30-D30 -> 12
... E34: =E33+B34+C34-D34 -> 12
A35: TOTALS | B35: =SUM(B4:B34) -> 42 | C35: =SUM(C4:C34) -> 0 | D35: =SUM(D4:D34) -> 30

Sheet WATER 500ML
B2: OPENING STOCK
A3: DATE | B3: WATER 500ML | C3: PURCHASE | D3: STOCK OUT | E3: BALANCE
A4: 46023 | B4: =24+9+4+3+48 -> 88 | D4: =24+9+4+3 -> 40 | E4: =B4+C4-D4 -> 48
A5: 46024 | C5: 48 | E5: =E4+B5+C5-D5 -> 96
A6: 14/1/2026 | D6: 24 | E6: =E5+B6+C6-D6 -> 72
E7: =E6+B7+C7-D7 -> 72
E8: =E7+B8+C8-D8 -> 72
E9: =E8+B9+C9-D9 -> 72
E10: =E9+B10+C10-D10 -> 72
E11: =E10+B11+C11-D11 -> 72
E12: =E11+B12+C12-D12 -> 72
E13: =E12+B13+C13-D13 -> 72
E14: =E13+B14+C14-D14 -> 72
E15: =E14+B15+C15-D15 -> 72
E16: =E15+B16+C16-D16 -> 72
E17: =E16+B17+C17-D17 -> 72
E18: =E17+B18+C18-D18 -> 72
... E20: =E19+B20+C20-D20 -> 72
E21: =E20+B21+C21-D21 -> 72 | G21: =24*3 -> 72
E22: =E21+B22+C22-D22 -> 72
E23: =E22+B23+C23-D23 -> 72
E24: =E23+B24+C24-D24 -> 72
E25: =E24+B25+C25-D25 -> 72
E26: =E25+B26+C26-D26 -> 72
E27: =E26+B27+C27-D27 -> 72
E28: =E27+B28+C28-D28 -> 72
E29: =E28+B29+C29-D29 -> 72
E30: =E29+B30+C30-D30 -> 72
E31: =E30+B31+C31-D31 -> 72
E32: =E31+B32+C32-D32 -> 72
E33: =E32+B33+C33-D33 -> 72
... E37: =E36+B37+C37-D37 -> 72
A38: TOTALS | B38: =SUM(B4:B36) -> 88 | C38: =SUM(C4:C36) -> 48 | D38: =SUM(D4:D37) -> 64

Sheet TRUST
B2: OPENING STOCK
A3: DATE | B3: TRUST | C3: PURCHASE | D3: STOCK OUT | E3: BALANCE
A4: 46023 | B4: =24+4+24 -> 52 | D4: 28 | E4: =B4+C4-D4 -> 24
A5: 16/01/2026 | C5: =24*2 -> 48 | E5: =E4+B5+C5-D5 -> 72
E6: =E5+B6+C6-D6 -> 72
E7: =E6+B7+C7-D7 -> 72
E8: =E7+B8+C8-D8 -> 72
E9: =E8+B9+C9-D9 -> 72
E10: =E9+B10+C10-D10 -> 72
E11: =E10+B11+C11-D11 -> 72
E12: =E11+B12+C12-D12 -> 72
E13: =E12+B13+C13-D13 -> 72
E14: =E13+B14+C14-D14 -> 72
E15: =E14+B15+C15-D15 -> 72
E16: =E15+B16+C16-D16 -> 72
E17: =E16+B17+C17-D17 -> 72
... E27: =E26+B27+C27-D27 -> 72
A28: TOTALS | B28: =SUM(B4:B27) -> 52 | C28: =SUM(C4:C27) -> 48 | D28: =SUM(D4:D27) -> 28

Sheet VASELINE
B2: OPENING STOCK
A3: DATE | B3: VASELINE | C3: PURCHASE | D3: STOCK OUT | E3: BALANCE
A4: 46023 | B4: =4+12 -> 16 | D4: 4 | E4: =B4+C4-D4 -> 12
A5: 14/1/2026 | D5: 12 | E5: =E4+B5+C5-D5 -> 0
A6: 17/01/2026 | C6: =12*2 -> 24 | E6: =E5+B6+C6-D6 -> 24
E7: =E6+B7+C7-D7 -> 24
E8: =E7+B8+C8-D8 -> 24
E9: =E8+B9+C9-D9 -> 24
E10: =E9+B10+C10-D10 -> 24
E11: =E10+B11+C11-D11 -> 24
E12: =E11+B12+C12-D12 -> 24
E13: =E12+B13+C13-D13 -> 24
E14: =E13+B14+C14-D14 -> 24
E15: =E14+B15+C15-D15 -> 24
E16: =E15+B16+C16-D16 -> 24
E17: =E16+B17+C17-D17 -> 24
E18: =E17+B18+C18-D18 -> 24
... E27: =E26+B27+C27-D27 -> 24
A28: TOTALS | B28: =SUM(B4:B27) -> 16 | C28: =SUM(C4:C27) -> 24 | D28: =SUM(D4:D27) -> 16

Sheet TOOTHPASTE & BRUSH
B2: OPENING STOCK
A3: DATE | B3: TOOTHPASTE & BRUSH | C3: PURCHASE | D3: STOCK OUT | E3: BALANCE
A4: 46023 | B4: =134+3 -> 137 | D4: 3 | E4: =B4+C4-D4 -> 134
A5: 14/1/2026 | D5: 20 | E5: =E4+B5+C5-D5 -> 114
E6: =E5+B6+C6-D6 -> 114
E7: =E6+B7+C7-D7 -> 114
E8: =E7+B8+C8-D8 -> 114
E9: =E8+B9+C9-D9 -> 114
E10: =E9+B10+C10-D10 -> 114
E11: =E10+B11+C11-D11 -> 114
E12: =E11+B12+C12-D12 -> 114
E13: =E12+B13+C13-D13 -> 114
E14: =E13+B14+C14-D14 -> 114
E15: =E14+B15+C15-D15 -> 114
E16: =E15+B16+C16-D16 -> 114
E17: =E16+B17+C17-D17 -> 114
... E27: =E26+B27+C27-D27 -> 114
A28: TOTALS | B28: =SUM(B4:B27) -> 137 | C28: =SUM(C4:C27) -> 0 | D28: =SUM(D4:D27) -> 23

Sheet SODA 500ML
B2: OPENING STOCK
A3: DATE | B3: SODA 500ML | C3: PURCHASE | D3: STOCK OUT | E3: BALANCE
A4: 46023 | B4: =17+2+24 -> 43 | D4: =19 -> 19 | E4: =B4+C4-D4 -> 24 | F4: Za Chupa
E5: =B5+C5-D5 -> 0
E6: =B6+C6-D6 -> 0
E7: =B7+C7-D7 -> 0
E8: =B8+C8-D8 -> 0
E9: =B9+C9-D9 -> 0
E10: =B10+C10-D10 -> 0
E11: =B11+C11-D11 -> 0
E12: =B12+C12-D12 -> 0
E13: =B13+C13-D13 -> 0
E14: =B14+C14-D14 -> 0
E15: =B15+C15-D15 -> 0
E16: =B16+C16-D16 -> 0
... E27: =B27+C27-D27 -> 0
A28: TOTALS | B28: =SUM(B4:B27) -> 43 | C28: =SUM(C4:C27) -> 0 | D28: =SUM(D4:D27) -> 19

Sheet PREDATOR 500ML
B2: OPENING STOCK
A3: DATE | B3: PREDATOR 500ML | C3: PURCHASE | D3: STOCK OUT | E3: BALANCE
A4: 46023 | B4: 11 | D4: 11 | E4: =B4+C4-D4 -> 0
E5: =E4+B5+C5-D5 -> 0
E6: =E5+B6+C6-D6 -> 0
E7: =E6+B7+C7-D7 -> 0
E8: =E7+B8+C8-D8 -> 0
E9: =E8+B9+C9-D9 -> 0
E10: =E9+B10+C10-D10 -> 0
E11: =E10+B11+C11-D11 -> 0
E12: =E11+B12+C12-D12 -> 0
E13: =E12+B13+C13-D13 -> 0
E14: =E13+B14+C14-D14 -> 0
E15: =E14+B15+C15-D15 -> 0
E16: =E15+B16+C16-D16 -> 0
... E27: =E26+B27+C27-D27 -> 0
A28: TOTALS | B28: =SUM(B4:B27) -> 11 | C28: =SUM(C4:C27) -> 0 | D28: =SUM(D4:D27) -> 11

Sheet PANADOL EXTRA
B2: OPENING STOCK | C2: IN PCS NOT PAIR
A3: DATE | B3: PANADOL EXTRA | C3: PURCHASE | D3: STOCK OUT | E3: BALANCE
A4: 46023 | B4: 120 | D4: 20 | E4: =B4+C4-D4 -> 100
E5: =E4+B5+C5-D5 -> 100
E6: =E5+B6+C6-D6 -> 100
E7: =E6+B7+C7-D7 -> 100
E8: =E7+B8+C8-D8 -> 100
E9: =E8+B9+C9-D9 -> 100
E10: =E9+B10+C10-D10 -> 100
E11: =E10+B11+C11-D11 -> 100
E12: =E11+B12+C12-D12 -> 100
E13: =E12+B13+C13-D13 -> 100
E14: =E13+B14+C14-D14 -> 100
E15: =E14+B15+C15-D15 -> 100
E16: =E15+B16+C16-D16 -> 100
... E27: =E26+B27+C27-D27 -> 100
A28: TOTALS | B28: =SUM(B4:B27) -> 120 | C28: =SUM(C4:C27) -> 0 | D28: =SUM(D4:D27) -> 20

Sheet MARA MOJA 
B2: OPENING STOCK | C2: IN PCS NOT PAIR
A3: DATE | B3: MARA MOJA | C3: PURCHASE | D3: STOCK OUT | E3: BALANCE
A4: 46023 | B4: =18+100 -> 118 | D4: 18 | E4: =B4+C4-D4 -> 100
E5: =E4+B5+C5-D5 -> 100
E6: =E5+B6+C6-D6 -> 100
E7: =E6+B7+C7-D7 -> 100
E8: =E7+B8+C8-D8 -> 100
E9: =E8+B9+C9-D9 -> 100
E10: =E9+B10+C10-D10 -> 100
E11: =E10+B11+C11-D11 -> 100
E12: =E11+B12+C12-D12 -> 100
E13: =E12+B13+C13-D13 -> 100
E14: =E13+B14+C14-D14 -> 100
E15: =E14+B15+C15-D15 -> 100
E16: =E15+B16+C16-D16 -> 100
... E27: =E26+B27+C27-D27 -> 100
A28: TOTALS | B28: =SUM(B4:B27) -> 118 | C28: =SUM(C4:C27) -> 0 | D28: =SUM(D4:D27) -> 18

Sheet VIM 500GM
B2: OPENING STOCK
A3: DATE | B3: VIM | C3: PURCHASE | D3: STOCK OUT | E3: BALANCE
A4: 46023 | B4: 13 | D4: 1 | E4: =B4+C4-D4 -> 12
E5: =E4+B5+C5-D5 -> 12
E6: =E5+B6+C6-D6 -> 12
E7: =E6+B7+C7-D7 -> 12
E8: =E7+B8+C8-D8 -> 12
E9: =E8+B9+C9-D9 -> 12
E10: =E9+B10+C10-D10 -> 12
E11: =E10+B11+C11-D11 -> 12
E12: =E11+B12+C12-D12 -> 12
E13: =E12+B13+C13-D13 -> 12
E14: =E13+B14+C14-D14 -> 12
E15: =E14+B15+C15-D15 -> 12
E16: =E15+B16+C16-D16 -> 12
... E27: =E26+B27+C27-D27 -> 12
A28: TOTALS | B28: =SUM(B4:B27) -> 13 | C28: =SUM(C4:C27) -> 0 | D28: =SUM(D4:D27) -> 1
